depictio/api/__init__.py
depictio/api/cache.py
depictio/api/main.py
depictio/api/run.py
depictio/api/v1/__init__.py
depictio/api/v1/backup_strategy_manager.py
depictio/api/v1/crypto.py
depictio/api/v1/db.py
depictio/api/v1/db_init.py
depictio/api/v1/deltatables_utils.py
depictio/api/v1/initialization.py
depictio/api/v1/key_utils.py
depictio/api/v1/key_utils_base.py
depictio/api/v1/s3.py
depictio/api/v1/utils.py
depictio/api/v1/configs/__init__.py
depictio/api/v1/configs/benchmark_dataset_generator.py
depictio/api/v1/configs/config.py
depictio/api/v1/configs/custom_logging.py
depictio/api/v1/configs/logging_init.py
depictio/api/v1/configs/settings_models.py
depictio/cli/__init__.py
depictio/cli/cli_logging.py
depictio/cli/depictio_cli.py
depictio/cli/cli/__init__.py
depictio/cli/cli/commands/__init__.py
depictio/cli/cli/commands/backup.py
depictio/cli/cli/commands/config.py
depictio/cli/cli/commands/data.py
depictio/cli/cli/commands/run.py
depictio/cli/cli/commands/standalone.py
depictio/cli/cli/utils/__init__.py
depictio/cli/cli/utils/api_calls.py
depictio/cli/cli/utils/backup_validation.py
depictio/cli/cli/utils/common.py
depictio/cli/cli/utils/config.py
depictio/cli/cli/utils/deltatables.py
depictio/cli/cli/utils/helpers.py
depictio/cli/cli/utils/multiqc_processor.py
depictio/cli/cli/utils/process.py
depictio/cli/cli/utils/rich_utils.py
depictio/cli/cli/utils/sample_mapping.py
depictio/cli/cli/utils/scan.py
depictio/cli/cli/utils/scan_utils.py
depictio/models/__init__.py
depictio/models/config.py
depictio/models/logging.py
depictio/models/s3_utils.py
depictio/models/utils.py
depictio/models/models/__init__.py
depictio/models/models/analytics.py
depictio/models/models/api.py
depictio/models/models/base.py
depictio/models/models/cli.py
depictio/models/models/dashboards.py
depictio/models/models/data_collections.py
depictio/models/models/deltatables.py
depictio/models/models/files.py
depictio/models/models/google_oauth.py
depictio/models/models/jbrowse.py
depictio_cli-0.5.3.dist-info/licenses/LICENSE
depictio_cli-0.5.3.dist-info/METADATA
depictio_cli-0.5.3.dist-info/WHEEL
depictio_cli-0.5.3.dist-info/entry_points.txt
depictio_cli-0.5.3.dist-info/top_level.txt
depictio_cli-0.5.3.dist-info/RECORD
