Metadata-Version: 2.4
Name: depictio-cli
Version: 0.5.3
Summary: Depictio CLI to interact with the Depictio API
Author-email: Thomas Weber <thomas.weber@embl.de>
License-Expression: MIT
Project-URL: Homepage, http://github.com/depictio/depictio
Classifier: Programming Language :: Python :: 3
Classifier: Operating System :: OS Independent
Requires-Python: >=3.11
License-File: LICENSE
Requires-Dist: boto3
Requires-Dist: colorlog
Requires-Dist: httpx==0.28.1
Requires-Dist: devtools
Requires-Dist: polars-lts-cpu[deltalake,excel,numpy,pandas,pyarrow]==1.19.0
Requires-Dist: deltalake==0.24.0
Requires-Dist: python-jose
Requires-Dist: pyyaml
Requires-Dist: typer
Requires-Dist: click<8.2.0,>=8.0.0
Requires-Dist: tomli
Requires-Dist: rich
Requires-Dist: pydantic[email]>=2.0.0
Requires-Dist: pydantic-settings>=2.0.0
Requires-Dist: beanie
Requires-Dist: python-dotenv
Requires-Dist: bleach
Requires-Dist: packaging
Provides-Extra: lts-cpu
Requires-Dist: polars-lts-cpu==1.19.0; extra == "lts-cpu"
Provides-Extra: multiqc
Requires-Dist: multiqc==1.31.0; extra == "multiqc"
Dynamic: license-file
